{
    "text": {
        "title": "Studio Light",
        "reset_button": "Start Over",
        "draw_message": "Friendly stalemate!",
        "win_message_template": "{winner} dominates!",
        "turn_message_template": "{player} to move"
    },
    "colors": {
        "title_text": "#1E1E1E",
        "status_text": "#4F4F4F",
        "board_background": "#F7F7F7",
        "cell_text": "#1E1E1E",
        "cell_fg": "#FFFFFF",
        "cell_hover": "#E0E0E0",
        "reset_fg": "#EFEFEF"
    },
    "layout": {
        "title_padding": 24,
        "status_padding": 12,
        "board_padding": [
            24,
            24
        ],
        "cell_size": [
            100,
            100
        ],
        "cell_spacing": 6,
        "reset_padding": 24
    }
}